odoo/addons/sale_project_task_recurrency/README.rst
odoo/addons/sale_project_task_recurrency/__init__.py
odoo/addons/sale_project_task_recurrency/__manifest__.py
odoo/addons/sale_project_task_recurrency/i18n/es.po
odoo/addons/sale_project_task_recurrency/i18n/it.po
odoo/addons/sale_project_task_recurrency/i18n/sale_project_task_recurrency.pot
odoo/addons/sale_project_task_recurrency/models/__init__.py
odoo/addons/sale_project_task_recurrency/models/product_template.py
odoo/addons/sale_project_task_recurrency/models/sale_order_line.py
odoo/addons/sale_project_task_recurrency/readme/CONFIGURE.md
odoo/addons/sale_project_task_recurrency/readme/CONTRIBUTORS.md
odoo/addons/sale_project_task_recurrency/readme/DESCRIPTION.md
odoo/addons/sale_project_task_recurrency/readme/USAGE.md
odoo/addons/sale_project_task_recurrency/static/description/icon.png
odoo/addons/sale_project_task_recurrency/static/description/index.html
odoo/addons/sale_project_task_recurrency/tests/__init__.py
odoo/addons/sale_project_task_recurrency/tests/test_product_task_recurrency.py
odoo/addons/sale_project_task_recurrency/views/product_template_views.xml
odoo_addon_sale_project_task_recurrency-18.0.1.0.0.3.dist-info/METADATA
odoo_addon_sale_project_task_recurrency-18.0.1.0.0.3.dist-info/WHEEL
odoo_addon_sale_project_task_recurrency-18.0.1.0.0.3.dist-info/top_level.txt
odoo_addon_sale_project_task_recurrency-18.0.1.0.0.3.dist-info/RECORD
